pylib25/__init__.py
pylib25-0.1.3.dist-info/METADATA
pylib25-0.1.3.dist-info/WHEEL
pylib25-0.1.3.dist-info/top_level.txt
pylib25-0.1.3.dist-info/RECORD
