Metadata-Version: 2.4
Name: pylib25
Version: 0.1.3
Summary: A simple library to illustrate how to deploy a Python library..
Home-page: https://github.com/fomalhaut88/pylib25
Author: Alexander Khlebushchev
License: MIT
Project-URL: Homepage, https://pypi.org/project/pylib25/
Project-URL: Documentation, https://fomalhaut88.github.io/pylib25/
Project-URL: Source, https://github.com/fomalhaut88/pylib25
Project-URL: Issues, https://github.com/fomalhaut88/pylib25/issues
Classifier: Development Status :: 5 - Production/Stable
Classifier: Intended Audience :: Developers
Classifier: Topic :: Software Development :: Libraries :: Python Modules
Classifier: License :: OSI Approved :: MIT License
Classifier: Programming Language :: Python :: 3.12
Classifier: Operating System :: OS Independent
Requires-Python: >=3.12
Dynamic: author
Dynamic: classifier
Dynamic: description
Dynamic: description-content-type
Dynamic: home-page
Dynamic: license
Dynamic: project-url
Dynamic: requires-python
Dynamic: summary
